cirrusvolume/__init__.py
cirrusvolume/graphene.py
cirrusvolume/precomputed.py
cirrusvolume/rules.py
cirrusvolume/volume.py
cirrus_volume-0.1.10.dist-info/LICENSE
cirrus_volume-0.1.10.dist-info/METADATA
cirrus_volume-0.1.10.dist-info/WHEEL
cirrus_volume-0.1.10.dist-info/top_level.txt
cirrus_volume-0.1.10.dist-info/RECORD
