Metadata-Version: 2.1
Name: cirrus-volume
Version: 0.1.10
Summary: Making happy (well-documented) CloudVolumes
Home-page: https://github.com/ZettaAI/cirrus-volume
Author: Nicholas Turner
Author-email: nturner@zetta.ai
License: UNKNOWN
Platform: UNKNOWN
License-File: LICENSE
Requires-Dist: provenance-toolbox
Requires-Dist: cloud-volume (<=8.19.3)
